LICENSE
simservice/PySimService.py
simservice/ServiceFunctionReceiver.py
simservice/ServiceFunctionRegistry.py
simservice/VERSION.txt
simservice/__init__.py
simservice/basics.py
simservice/managers.py
simservice/messages.py
simservice/service_containers.py
simservice/service_factory.py
simservice/service_wraps.py
simservice/utils.py
simservice-0.1.1.dist-info/LICENSE
simservice-0.1.1.dist-info/METADATA
simservice-0.1.1.dist-info/WHEEL
simservice-0.1.1.dist-info/top_level.txt
simservice-0.1.1.dist-info/RECORD
