Metadata-Version: 2.1
Name: simservice
Version: 0.1.1
Summary: A library for building simulation services in Python
Home-page: https://github.com/tjsego/simservice
Author: T.J. Sego
Author-email: timothy.sego@medicine.ufl.edu
License: MIT
Classifier: Development Status :: 3 - Alpha
Classifier: Intended Audience :: Science/Research
Classifier: License :: OSI Approved :: MIT License
Classifier: Operating System :: OS Independent
Classifier: Programming Language :: Python :: 3.6
Classifier: Programming Language :: Python :: 3.7
Classifier: Programming Language :: Python :: 3.8
Classifier: Programming Language :: Python :: 3.9
Classifier: Programming Language :: Python :: 3.10
Requires-Python: >=3.6
License-File: LICENSE
